metadata_tagger/__init__.py
metadata_tagger/object_tagger.py
metadata_tagger/py.typed
metadata_tagger/extractors/__init__.py
metadata_tagger/extractors/pdf_metadata_extractor.py
metadata_tagger/extractors/picture_metadata_extractor.py
s3_metadata_tagger-1.0.1.dist-info/LICENSE
s3_metadata_tagger-1.0.1.dist-info/METADATA
s3_metadata_tagger-1.0.1.dist-info/WHEEL
s3_metadata_tagger-1.0.1.dist-info/top_level.txt
s3_metadata_tagger-1.0.1.dist-info/RECORD
