Metadata-Version: 2.1
Name: s3-metadata-tagger
Version: 1.0.1
Summary: A package to add metadata tags to objects saved in s3
License: BSD 3-Clause License        
Project-URL: Homepage, https://github.com/DDS-GmbH/s3-metadata-tagger-lib/
Project-URL: Bug Tracker, https://github.com/DDS-GmbH/s3-metadata-tagger-lib/issues
Keywords: aws,s3,metadata
Classifier: Development Status :: 5 - Production/Stable
Classifier: Programming Language :: Python :: 3
Classifier: License :: OSI Approved :: MIT License
Classifier: Operating System :: OS Independent
Classifier: Intended Audience :: Developers
Classifier: License :: OSI Approved :: BSD License
Classifier: Operating System :: POSIX :: Linux
Classifier: Topic :: Multimedia
Requires-Python: >=3.7
License-File: LICENSE
Requires-Dist: autopep8
Requires-Dist: boto3
Requires-Dist: boto3-stubs
Requires-Dist: botocore
Requires-Dist: botocore-stubs
Requires-Dist: mypy-boto3-s3
Requires-Dist: pycodestyle
Requires-Dist: typing-extensions
Provides-Extra: pdf
Requires-Dist: PyPDF2 ; extra == 'pdf'
Provides-Extra: picture
Requires-Dist: Pillow ; extra == 'picture'
Requires-Dist: types-Pillow ; extra == 'picture'
